README.txt
rander.py
setup.py
rander.egg-info/PKG-INFO
rander.egg-info/SOURCES.txt
rander.egg-info/dependency_links.txt
rander.egg-info/top_level.txt
rander.egg-info/zip-safe