Metadata-Version: 1.1
Name: rander
Version: 1.0.0
Summary: Generate a randomized sequence of numbers
Home-page: https://github.com/15281029/rander
Author: Zhangbo
Author-email: 15281029@bjtu.edu.cn
License: MIT
Platform: UNKNOWN
Classifier: License :: OSI Approved :: MIT License
Classifier: Programming Language :: Python
Classifier: Intended Audience :: Developers
Classifier: Operating System :: OS Independent
